proof_of_train/__init__.py
proof_of_train/abi.json
proof_of_train/model_metadata.py
proof_of_train/proof_of_train.py
proof_of_train-0.3.0.dist-info/METADATA
proof_of_train-0.3.0.dist-info/WHEEL
proof_of_train-0.3.0.dist-info/RECORD
