Metadata-Version: 2.1
Name: proof-of-train
Version: 0.3.0
Summary: Proof of Train SDK for submitting and verifying model training metadata on blockchain.
Author: Thomas
Author-email: wxy_000000@qq.com
Requires-Python: >=3.12,<4.0
Classifier: Programming Language :: Python :: 3
Classifier: Programming Language :: Python :: 3.12
Requires-Dist: pytest (>=8.2.1,<9.0.0)
Requires-Dist: web3 (>=6.19.0,<7.0.0)
